<?xml version="1.0" encoding="utf-8"?>
<tt xmlns="http://www.w3.org/ns/ttml" xmlns:tts="http://www.w3.org/ns/ttml#styling" ttp:version="2" xmlns:ttm="http://www.w3.org/ns/ttml#metadata" xmlns:ttp="http://www.w3.org/ns/ttml#parameter" xml:lang="te-IN">
 <head>
  <styling>
   <style xml:id="s0" tts:fontFamily="sansSerif" tts:fontStyle="italic" tts:color="white" tts:fontWeight="normal" tts:fontSize="100%"></style>
   <style xml:id="s1" tts:fontFamily="sansSerif" tts:fontStyle="normal" tts:color="white" tts:fontWeight="normal" tts:fontSize="100%"></style>
  </styling>
  <layout>
   <region xml:id="r0" tts:extent="100% 15%" tts:origin="0% 85%" tts:displayAlign="after" tts:textAlign="center"></region>
   <region xml:id="r1" tts:extent="100% 15%" tts:origin="0% 0%" tts:displayAlign="before" tts:textAlign="center"></region>
  </layout>
 </head>
 <body style="s1">
  <div>
   <p begin="00:01:24.666" end="00:01:27.583" region="r0">ద పెరిఫరల్</p>
   <p begin="00:01:57.458" end="00:02:00.000" region="r1">లండన్ 2099</p>
   <p begin="00:02:39.708" end="00:02:42.208" region="r0">నువ్వు ఎలాంటి చెత్తలోకి దిగావు, ఎలీటా?</p>
   <p begin="00:02:42.541" end="00:02:44.875" region="r0">నువ్వు నన్ను దింపిన చెత్త అంటున్నావా?</p>
   <p begin="00:02:47.750" end="00:02:51.000" region="r0">అలాంటి ప్రమాదకరమైన స్నేహితులతో<br />స్నేహం చేస్తావని ఎవరు ఊహిస్తారు?</p>
   <p begin="00:02:53.583" end="00:02:56.041" region="r0">ఒకసారి షూస్ లేకుండా<br />నేను ఆరు నెలలు ఉన్నాను.</p>
   <p begin="00:02:56.125" end="00:02:57.291" region="r0">గుర్తుందా?</p>
   <p begin="00:02:57.875" end="00:03:01.958" region="r0">మనిషి పాదాలు రాటుదేలి గట్టిగా మారడం<br />లేదా మృదువుగా మారడం అద్భుతం.</p>
   <p begin="00:03:02.041" end="00:03:05.708" region="r0">తమ పరిసరాలకు అనుగుణంగా.<br />అంటే ఆ మనిషి మనసులా.</p>
   <p begin="00:03:08.750" end="00:03:11.291" region="r0">వాటికి ఏమయిందో గుర్తుందా? నా షూస్‌‌కు?</p>
   <p begin="00:03:12.583" end="00:03:13.791" region="r0">వాటిని నాకు ఇచ్చావు.</p>
   <p begin="00:03:16.208" end="00:03:18.416" region="r0">నిన్ను తొలిసారి కలిసినప్పుడు, శపథం చేశా.</p>
   <p begin="00:03:18.708" end="00:03:20.166" region="r0">వీలైతే నిన్ను కాపాడుతానని.</p>
   <p begin="00:03:20.250" end="00:03:21.125" region="r0">కాపాడావు కూడా.</p>
   <p begin="00:03:22.583" end="00:03:23.458" region="r0">కాపాడానా?</p>
   <p begin="00:03:25.166" end="00:03:26.416" region="r0">ఏం చేస్తున్నావు, ఎలీటా?</p>
   <p begin="00:03:28.958" end="00:03:30.333" region="r0">ప్రపంచాన్ని కాపాడుతున్నా.</p>
   <p begin="00:03:30.416" end="00:03:32.875" region="r0">మన ప్రపంచం ఆ స్థాయిని దాటిపోయింది.<br />నువ్వే అన్నావు.</p>
   <p begin="00:03:32.958" end="00:03:35.000" region="r0">నేను మన ప్రపంచం అని చెప్పలేదే.</p>
   <p begin="00:03:42.291" end="00:03:43.250" region="r0">ఉంటాను, వూల్ఫ్.</p>
   <p begin="00:03:45.041" end="00:03:45.916" region="r0">ఎలీటా?</p>
   <p begin="00:03:49.708" end="00:03:50.708" region="r0">ఎలీటా?</p>
   <p begin="00:04:28.666" end="00:04:32.041" region="r1">బ్లూ రిడ్జ్ పర్వతాలు<br />2032</p>
   <p begin="00:05:14.166" end="00:05:15.333" region="r0">మార్నింగ్, అమ్మా.</p>
   <p begin="00:05:16.333" end="00:05:19.250" region="r0">నీ కోసం కాఫీ తెచ్చాను.<br />జాగ్రత్త. కొంచెం వేడిగా ఉంది.</p>
   <p begin="00:05:19.333" end="00:05:20.166" region="r0">థాంక్యూ.</p>
   <p begin="00:05:20.250" end="00:05:23.125" region="r0">తీసుకో. నీకొక శాండ్విచ్ చేశా.<br />ఫ్రిడ్జ్‌లో ఉంచాను.</p>
   <p begin="00:05:23.208" end="00:05:25.291" region="r0">బర్టన్‌కి కావాలంటే, వాడే చేసుకుంటాడు.</p>
   <p begin="00:05:25.375" end="00:05:27.791" region="r0">నిన్న నీది తిన్నాడు. మాట మార్చకు.</p>
   <p begin="00:05:27.875" end="00:05:29.041" region="r0">నాకు ఆకలి అనిపించలేదు.</p>
   <p begin="00:05:32.291" end="00:05:33.833" region="r0">నువ్వు బరువు కోల్పోకూడదు.</p>
   <p begin="00:05:33.916" end="00:05:35.833" region="r0">మళ్ళీ ఆసుపత్రిపాలు అవుతావు.</p>
   <p begin="00:05:41.958" end="00:05:42.916" region="r0">బర్టన్!</p>
   <p begin="00:05:44.208" end="00:05:45.166" region="r0">ఛత్.</p>
   <p begin="00:05:55.041" end="00:05:56.250" region="r0">బర్టన్, తలుపు తెరువు!</p>
   <p begin="00:05:57.333" end="00:05:58.166" region="r0">బర్టన్.</p>
   <p begin="00:06:02.333" end="00:06:05.541" region="r0">అమ్మ వేసుకున్న టామొసీన్ 10 ఎంజీలే<br />ఎందుకుందో చెప్తావా?</p>
   <p begin="00:06:05.625" end="00:06:07.333" region="r0">ఇది చూసుకో. బాత్రూంకి వెళ్ళాలి.</p>
   <p begin="00:06:07.416" end="00:06:08.875" region="r0">మాత్రలు మారుస్తున్నావా?</p>
   <p begin="00:06:10.083" end="00:06:12.791" region="r0">బర్టన్, అమ్మ మాత్రలతో నీవి మారుస్తున్నావా?</p>
   <p begin="00:06:12.875" end="00:06:15.708" region="r0">దేవుడా, ఫ్లిన్.<br />నేనలా చేస్తానని అనుకుంటున్నావా?</p>
   <p begin="00:06:15.791" end="00:06:17.583" region="r0">ఆమెకు ఉన్నది 10 ఎంజీల మాత్ర.</p>
   <p begin="00:06:17.666" end="00:06:19.416" region="r0">కేవలం ఒక్కటే ఉంది.</p>
   <p begin="00:06:19.500" end="00:06:23.333" region="r0">అంటే నువ్వు మార్చుకోవడమే కాదు,<br />దొంగలిస్తున్నావు కూడా.</p>
   <p begin="00:06:23.416" end="00:06:24.708" region="r0">నాకు డబ్బు కావాలి.</p>
   <p begin="00:06:24.791" end="00:06:26.583" region="r0">-ఎంత?<br />-నీ దగ్గర ఎంతుంది?</p>
   <p begin="00:06:26.666" end="00:06:29.666" region="r0">తరువాతి స్థాయికెళ్తే, వెయ్యి వస్తాయి.<br />నువ్వూ సాయం చేయవచ్చు.</p>
   <p begin="00:06:29.750" end="00:06:32.708" region="r0">-వాటితో ఒక మాత్రే వస్తుంది.<br />-ఒక రోజుకి సరిపోతుందిగా?</p>
   <p begin="00:06:33.375" end="00:06:37.375" region="r0">ఈ రాత్రి నాకో పెద్ద అవకాశం రాబోతోంది,<br />మిగిలిన మాత్రలు రేపటికి వచ్చేస్తాయి.</p>
   <p begin="00:06:38.541" end="00:06:39.375" region="r0">స్థితి చెప్పు.</p>
   <p begin="00:06:39.458" end="00:06:40.291" region="r0">హెడ్‌సెట్ కనెక్ట్ అయింది</p>
   <p begin="00:06:40.375" end="00:06:42.458" region="r0">ఇంట్లో నాజీ దళముంది.<br />పశువులపాకలో ఉన్నాం.</p>
   <p begin="00:06:42.541" end="00:06:43.500" region="r0">"మేము" అంటే?</p>
   <p begin="00:06:43.583" end="00:06:46.125" region="r0">నేను, రీస్ అలాగే కాలిఫోర్నియా నుండి ఒకడు.</p>
   <p begin="00:06:46.208" end="00:06:48.208" region="r0">20వ స్థాయి దాటడానికి <br />తీసుకున్నాడు.</p>
   <p begin="00:06:48.291" end="00:06:51.166" region="r0">ఎప్పుడూ "నిదానం" అంటుంటాడు.<br />అది పరమ చిరాకుగా ఉంది.</p>
   <p begin="00:06:51.250" end="00:06:52.708" region="r0">రీస్ టోపీ పెట్టుకున్నాడు.</p>
   <p begin="00:06:53.916" end="00:06:56.125" region="r0">త్వరగా! నాకు ఇప్పటికే ఆలస్యమైంది.</p>
   <p begin="00:06:58.666" end="00:06:59.958" region="r0">ఆట కొనసాగుతుంది: ఈజీ ఐస్</p>
   <p begin="00:07:00.333" end="00:07:01.833" region="r0">ఈజీ ఐస్<br />రీస్106 - టామ్‌217</p>
   <p begin="00:07:20.500" end="00:07:21.958" region="r0">మీకు అసలు కొంచమైనా--</p>
   <p begin="00:07:22.041" end="00:07:23.208" region="r0">మంచితనం లేదా?</p>
   <p begin="00:07:23.958" end="00:07:25.916" region="r0">కనీసం ఆ గొర్రెల్ని వదిలేయచ్చుగా.</p>
   <p begin="00:07:35.500" end="00:07:38.833" region="r0">నాకు నీ టోపీ నచ్చింది, రీస్.<br />చాలా చక్కగా ఉంది.</p>
   <p begin="00:07:38.916" end="00:07:39.916" region="r0">ఫ్లిన్?</p>
   <p begin="00:07:40.000" end="00:07:41.000" region="r0"><span style="s0">బర్టన్ ఎక్కడ?</span></p>
   <p begin="00:07:41.083" end="00:07:42.083" region="r0">బాత్రూమ్‌కి వెళ్ళాడు.</p>
   <p begin="00:07:42.875" end="00:07:46.041" region="r0">-దేని కోసం వెతుతుకున్నాం?<br />-అదొక మ్యాప్ అయ్యుండాలి.</p>
   <p begin="00:07:47.000" end="00:07:47.875" region="r0">మీరు కనిపెట్టారా?</p>
   <p begin="00:07:50.750" end="00:07:51.958" region="r0">ఏం చేస్తున్నావు?</p>
   <p begin="00:07:53.083" end="00:07:54.125" region="r0">ఆ తలుపు తెరువు.</p>
   <p begin="00:08:10.916" end="00:08:11.875" region="r0">వచ్చేశాను.</p>
   <p begin="00:08:11.958" end="00:08:12.958" region="r0">ఒక నిమిషం ఆగు.</p>
   <p begin="00:08:14.291" end="00:08:15.625" region="r0">ముందుకు కదలండి!</p>
   <p begin="00:08:45.750" end="00:08:46.666" region="r0">నిదానం, బాబు.</p>
   <p begin="00:08:48.333" end="00:08:51.250" region="r0">-ఆ మ్యాప్ మీరెందుకు కనుక్కోలేదో తెలుసా?<br />-ఎందుకు?</p>
   <p begin="00:08:51.333" end="00:08:52.916" region="r0">అదింకా రాలేదు.</p>
   <p begin="00:08:58.333" end="00:08:59.958" region="r0">నా ఫోనుకి డబ్బులు పంపు.</p>
   <p begin="00:09:01.666" end="00:09:02.750" region="r0">ఫర్వాలేదు.</p>
   <p begin="00:09:05.791" end="00:09:06.666" region="r0">రీస్!</p>
   <p begin="00:09:08.583" end="00:09:09.958" region="r0">అసలేం జరిగి చచ్చింది?</p>
   <p begin="00:09:11.166" end="00:09:12.166" region="r0">ఫ్లిన్ చేసిన పని.</p>
   <p begin="00:09:50.625" end="00:09:52.166" region="r0">ఏటీఎం - హెఫ్టీ<br />24 గంటల నగదు</p>
   <p begin="00:09:53.041" end="00:09:53.875" region="r0">విత్ డ్రా</p>
   <p begin="00:10:12.166" end="00:10:15.250" region="r0">జరిగే ప్రతి విత్ డ్రాయల్ ని<br />హోంశాఖ పరిశీలిస్తుందా?</p>
   <p begin="00:10:15.333" end="00:10:17.041" region="r0">అలా చేయడం మంచిదే.</p>
   <p begin="00:10:17.125" end="00:10:20.208" region="r0">ఈ రోజుల్లో ఏదో తేడా పని చేయటానికే<br />నగదు వాడుతున్నారు.</p>
   <p begin="00:10:20.291" end="00:10:24.166" region="r0">నీ మాటల్లో ఏదైనా ప్రశ్న దాగుందా, టామీ?</p>
   <p begin="00:10:26.083" end="00:10:27.541" region="r0">మీ అమ్మకు ఎలా ఉంది?</p>
   <p begin="00:10:28.333" end="00:10:29.291" region="r0">ఆమె బాగుంది.</p>
   <p begin="00:10:29.833" end="00:10:31.250" region="r0">అవును. అడిగినందుకు థాంక్స్.</p>
   <p begin="00:10:33.291" end="00:10:34.500" region="r0">ఇక్కడేం చేస్తున్నావు?</p>
   <p begin="00:10:34.583" end="00:10:37.250" region="r0">మేకన్, ఎడ్వర్డ్‌లు<br />చివరికి ఏదైనా నేరం చేశారా?</p>
   <p begin="00:10:37.333" end="00:10:40.291" region="r0">ఇంకా చేయలేదు, కానీ కొంత సమయంలో చేస్తారు.</p>
   <p begin="00:10:40.791" end="00:10:43.125" region="r0">డీడీ కోసం ఒక ఆర్డర్ ఇవ్వడానికి వచ్చాను.</p>
   <p begin="00:10:43.208" end="00:10:45.833" region="r0">మా పెళ్ళి కేకుపై అలంకరణల ముద్రణకు.</p>
   <p begin="00:10:49.791" end="00:10:53.750" region="r0">నేను వెళ్ళి వారికి సాయం చేయాలేమో.</p>
   <p begin="00:10:56.416" end="00:10:58.666" region="r0">పెద్దవారి పర్యవేక్షణ లేకపోతే చెడగొడతారు.</p>
   <p begin="00:10:59.583" end="00:11:03.125" region="r0">బిల్లీ యాన్ నీ కోసం వేచి చూస్తోంది.<br />కొన్ని నబిన్లతో.</p>
   <p begin="00:11:03.208" end="00:11:05.541" region="r0">-నిన్ను హెచ్చరిస్తున్నా.<br />-థాంక్యూ.</p>
   <p begin="00:11:06.666" end="00:11:07.875" region="r0">ఉంటాను, టామీ.</p>
   <p begin="00:11:14.791" end="00:11:16.958" region="r0"><span style="s0">నువ్వేమీ చెప్పలేదు కదా?</span></p>
   <p begin="00:11:17.041" end="00:11:19.541" region="r0"><span style="s0">-నేను ఏం చెప్పి ఉండాలి?</span><br /><span style="s0">-ఇలా చెప్పుంటే...</span></p>
   <p begin="00:11:19.625" end="00:11:21.125" region="r0">ఫారెవర్ ఫాబ్<br />3డీ ప్రింటింగ్</p>
   <p begin="00:11:21.208" end="00:11:25.250" region="r0"><span style="s0">"నీలా ఉంటే ఎలా ఉంటుందా అని ఊహిస్తున్నాను,</span></p>
   <p begin="00:11:25.791" end="00:11:26.875" region="r0">"అలా నిలబడి ఉంటే."</p>
   <p begin="00:11:26.958" end="00:11:30.916" region="r0">ఆ తర్వాత, "కానీ ఊహించలేను.<br />నువ్వు చాలా అందగాడివి.</p>
   <p begin="00:11:31.541" end="00:11:35.000" region="r0">"సింహం లోపల నేను ఉన్నట్టుగా<br />ఊహించుకున్నట్టు అనిపిస్తోంది."</p>
   <p begin="00:11:35.958" end="00:11:37.166" region="r0">బిల్లీ, సింహమా?</p>
   <p begin="00:11:37.250" end="00:11:38.666" region="r0">ఏదో ఒక జంతువు.</p>
   <p begin="00:11:38.750" end="00:11:41.291" region="r0">ఆ తర్వాత, కైపుతో ఆకట్టుకునేలా,</p>
   <p begin="00:11:41.708" end="00:11:43.375" region="r0">"నీ సమయానికి విలువనిస్తావా?"</p>
   <p begin="00:11:43.458" end="00:11:45.625" region="r0">"అవును" అంటాడు, ఎందుకంటే వేరే ఏం అనగలడు?</p>
   <p begin="00:11:45.708" end="00:11:49.500" region="r0">ఇక నువ్వు, "ఈ విలువైన క్షణాలని<br />ఇలా మాటల్లో వృధా చేయడమెందుకు..."</p>
   <p begin="00:11:49.583" end="00:11:51.333" region="r0">ఫ్లిన్? ఇక్కడ టామీ ఆర్డర్ ఉంది.</p>
   <p begin="00:11:51.416" end="00:11:53.708" region="r0">"...మనం చెమటలు పట్టిన వాటిని రుద్దుతూ..."</p>
   <p begin="00:11:53.791" end="00:11:56.875" region="r0">ఇద్దరు వరులను, ఒక వధువును<br />ఎందుకు ఆర్డర్ చేశారంటావు?</p>
   <p begin="00:11:56.958" end="00:11:59.125" region="r0">"బిల్లీ యాన్! నబిన్ తీసుకోనా?"<br />అని అడగొచ్చు.</p>
   <p begin="00:11:59.208" end="00:12:00.958" region="r0">నువ్వు పత్రం తప్పుగా చదవటం వల్లా?</p>
   <p begin="00:12:03.125" end="00:12:03.958" region="r0">ఛత్.</p>
   <p begin="00:12:07.958" end="00:12:08.833" region="r0">లెక్క సరిపోయింది.</p>
   <p begin="00:12:11.791" end="00:12:14.083" region="r0">"నిన్ను చూడటం బాగుంది!<br />నబిన్స్‌కు థాంక్స్!"</p>
   <p begin="00:12:16.125" end="00:12:17.375" region="r0">నీకిది చెప్పాల్సిందే.</p>
   <p begin="00:12:17.458" end="00:12:21.875" region="r0">ఈ మూర్ఖుల సంతలో నీ నైపుణ్యాలు,<br />వ్యక్తిత్వం వృధా అవుతున్నాయి.</p>
   <p begin="00:12:21.958" end="00:12:23.041" region="r0"><span style="s0">15వ ప్రింటర్ ఆగింది.</span></p>
   <p begin="00:12:23.125" end="00:12:26.250" region="r0">ముఖ్యంగా వీడియో గేమ్స్ ఆడడం ద్వారా </p>
   <p begin="00:12:26.333" end="00:12:27.750" region="r0">తేలిగ్గా డబ్బు సంపాదించచ్చు.</p>
   <p begin="00:12:27.833" end="00:12:30.750" region="r0">ధనవంతులకు పనులు చేస్తూ<br />బర్టన్ ఎంత సంపాదిస్తున్నాడు?</p>
   <p begin="00:12:30.833" end="00:12:32.250" region="r0">వాడి అర్హతకు మించే.</p>
   <p begin="00:12:32.333" end="00:12:35.250" region="r0">నువ్వింకా ఎక్కువ సంపాదించవచ్చు.<br />తన అవతార్‌ని వాడితే.</p>
   <p begin="00:12:35.333" end="00:12:37.291" region="r0">నువ్వు అమ్మాయని వాళ్ళకు తెలియదు.</p>
   <p begin="00:12:37.375" end="00:12:40.125" region="r0">వాటి జోలికి ఇక వెళ్ళను, బిల్లీ యాన్.<br />చెప్పాగా.</p>
   <p begin="00:12:40.208" end