<?xml version='1.0' encoding='UTF-8' standalone='yes' ?>
<settings version="169">
  <setting id="59" name="com.amazon.tv.settings.ACCESSIBILITY_VIDEO_DESCRIPTION" value="0" package="android" defaultValue="0" defaultSysSet="true" />
  <setting id="43" name="low_battery_sound_timeout" value="0" package="android" defaultValue="0" defaultSysSet="true" />
  <setting id="34" name="car_undock_sound" value="/system/media/audio/ui/Undock.ogg" package="android" defaultValue="/system/media/audio/ui/Undock.ogg" defaultSysSet="true" />
  <setting id="252" name="bluetooth_headset_priority_D0:C2:4E:5F:E9:21" value="0" package="com.android.bluetooth" defaultValue="0" defaultSysSet="true" />
  <setting id="116" name="show_home_drop_in" value="1" package="com.android.settings" defaultValue="1" defaultSysSet="true" />
  <setting id="340" name="bluetooth_a2dp_src_priority_F4:5C:89:C7:54:F0" value="100" package="com.android.bluetooth" defaultValue="100" defaultSysSet="true" />
  <setting id="10" name="window_animation_scale" value="1.0" package="android" defaultValue="1.0" defaultSysSet="true" />
  <setting id="200" name="atz_response_provider" value='{"timeStampInMillis":1697162135240,"isSuccess":true,"updatedTimeZone":"America\/New_York","countryCode":"US","dcasUpdatedTime":1697162135239}' package="com.amazon.kindleautomatictimezone" defaultValue='{"timeStampInMillis":1697162135240,"isSuccess":true,"updatedTimeZone":"America\/New_York","countryCode":"US","dcasUpdatedTime":1697162135239}' defaultSysSet="true" />
  <setting id="76" name="show_zen_settings_suggestion" value="1" package="android" defaultValue="1" defaultSysSet="true" />
  <setting id="9" name="mode_ringer" value="2" package="android" defaultValue="2" defaultSysSet="true" />
  <setting id="38" name="default_install_location" value="0" package="android" defaultValue="0" defaultSysSet="true" />
  <setting id="23" name="wifi_display_on" value="0" package="android" defaultValue="0" defaultSysSet="true" />
  <setting id="46" name="device_name" value="AEOAT" package="android" defaultValue="AEOAT" defaultSysSet="true" />
  <setting id="14" name="wifi_networks_available_notification_on" value="1" package="android" defaultValue="1" defaultSysSet="true" />
  <setting id="81" name="zen_settings_updated" value="1" package="android" defaultValue="1" defaultSysSet="true" />
  <setting id="30" name="dock_sounds_enabled_when_accessbility" value="0" package="android" defaultValue="0" defaultSysSet="true" />
  <setting id="15" name="bluetooth_on" value="1" package="android" defaultValue="1" defaultSysSet="true" />
  <setting id="65" name="support_use_sys_time_in_tunnel" value="0" package="android" defaultValue="0" defaultSysSet="true" />
  <setting id="19" name="mobile_data" value="1" package="android" defaultValue="1" defaultSysSet="true" />
  <setting id="247" name="network_watchlist_last_report_time" value="1697860800000" package="android" defaultValue="1697860800000" defaultSysSet="true" />
  <setting id="47" name="database_creation_buildid" value="PS7560.3673N" package="android" defaultValue="PS7560.3673N" defaultSysSet="true" />
  <setting id="84" name="nrdp_audio_platform_capabilities" value='{"audiocaps":{"continuousAudio":true,"pcm":{"mixing":true,"transition":"ease"},"ddplus":{"mixing":true,"transition":"ease"},"atmos":{"enabled":false,"mixing":true,"transition":"ease"}}}' package="android" defaultValue='{"audiocaps":{"continuousAudio":true,"pcm":{"mixing":true,"transition":"ease"},"ddplus":{"mixing":true,"transition":"ease"},"atmos":{"enabled":false,"mixing":true,"transition":"ease"}}}' defaultSysSet="true" />
  <setting id="39" name="emergency_tone" value="0" package="android" defaultValue="0" defaultSysSet="true" />
  <setting id="74" name="max_sound_trigger_detection_service_ops_per_day" value="1000" package="android" defaultValue="1000" defaultSysSet="true" />
  <setting id="254" name="bluetooth_headset_priority_80:8A:BD:97:84:13" value="0" package="com.android.bluetooth" defaultValue="0" defaultSysSet="true" />
  <setting id="67" name="add_users_when_locked" value="0" package="android" defaultValue="0" defaultSysSet="true" />
  <setting id="36" name="dock_audio_media_enabled" value="1" package="android" defaultValue="1" defaultSysSet="true" />
  <setting id="250" name="bluetooth_headset_priority_E0:03:6B:50:AB:8E" value="0" package="com.android.bluetooth" defaultValue="0" defaultSysSet="true" />
  <setting id="122" name="weather_alerts" value="1" package="com.android.settings" defaultValue="1" defaultSysSet="true" />
  <setting id="99" name="adb_enabled" value="0" package="android" defaultValue="0" defaultSysSet="true" />
  <setting id="26" name="trusted_sound" value="/system/media/audio/ui/Trusted.ogg" package="android" defaultValue="/system/media/audio/ui/Trusted.ogg" defaultSysSet="true" />
  <setting id="25" name="unlock_sound" value="/system/media/audio/ui/Unlock.ogg" package="android" defaultValue="/system/media/audio/ui/Unlock.ogg" defaultSysSet="true" />
  <setting id="258" name="bluetooth_a2dp_src_priority_98:06:3C:25:FF:CF" value="-1" package="com.android.bluetooth" defaultValue="-1" defaultSysSet="true" />
  <setting id="2" name="airplane_mode_radios" value="cell,bluetooth,wifi,nfc,wimax" package="android" defaultValue="cell,bluetooth,wifi,nfc,wimax" defaultSysSet="true" />
  <setting id="22" name="wifi_max_dhcp_retry_count" value="9" package="android" defaultValue="9" defaultSysSet="true" />
  <setting id="56" name="perfboost_rotation_duration" value="500" package="android" defaultValue="500" defaultSysSet="true" />
  <setting id="3" name="airplane_mode_toggleable_radios" value="bluetooth,wifi,nfc" package="android" defaultValue="bluetooth,wifi,nfc" defaultSysSet="true" />
  <setting id="45" name="heads_up_notifications_enabled" value="1" package="android" defaultValue="1" defaultSysSet="true" />
  <setting id="98" name="low_power" value="0" package="android" defaultValue="0" defaultSysSet="true" />
  <setting id="146" name="com.amazon.oobe.fetched.postal_code" value="21042-2752" package="com.android.settings" defaultValue="21042-2752" defaultSysSet="true" />
  <setting id="259" name="bluetooth_headset_priority_98:06:3C:25:FF:CF" value="0" package="com.android.bluetooth" defaultValue="0" defaultSysSet="true" />
  <setting id="100" name="policy_control" value="immersive.full=*,-us.zoom.zoompresence" package="com.android.systemui" defaultValue="immersive.full=*,-us.zoom.zoompresence" defaultSysSet="true" />
  <setting id="79" name="charging_vibration_enabled" value="1" package="android" defaultValue="1" defaultSysSet="true" />
  <setting id="117" name="show_home_notifications" value="1" package="com.android.settings" defaultValue="1" defaultSysSet="true" />
  <setting id="64" name="use_external_surround_sound_flag" value="0" package="android" defaultValue="0" defaultSysSet="true" />
  <setting id="85" name="zen_mode_ringer_level" value="2" package="android" defaultValue="2" defaultSysSet="true" />
  <setting id="115" name="ttt_discovery_card" value="1" package="com.android.settings" defaultValue="1" defaultSysSet="true" />
  <setting id="41" name="preferred_network_mode" value="0" package="android" defaultValue="0" defaultSysSet="true" />
  <setting id="120" name="a2s_recent_used_skill" value="1" package="com.android.settings" defaultValue="1" defaultSysSet="true" />
  <setting id="68" name="bluetooth_disabled_profiles" value="0" package="android" defaultValue="0" defaultSysSet="true" />
  <setting id="32" name="desk_undock_sound" value="/system/media/audio/ui/Undock.ogg" package="android" defaultValue="/system/media/audio/ui/Undock.ogg" defaultSysSet="true" />
  <setting id="73" name="zen_duration" value="0" package="android" defaultValue="0" defaultSysSet="true" />
  <setting id="71" name="mobile_data_always_on" value="1" package="android" defaultValue="1" defaultSysSet="true" />
  <setting id="87" name="webview_provider" value="com.amazon.webview.chromium" package="android" defaultValue="com.amazon.webview.chromium" defaultSysSet="true" />
  <setting id="8" name="wifi_sleep_policy" value="2" package="android" defaultValue="2" defaultSysSet="true" />
  <setting id="338" name="bluetooth_a2dp_src_priority_F4:4E:FD:C6:29:FC" value="100" package="com.android.bluetooth" defaultValue="100" defaultSysSet="true" />
  <setting id="29" name="dock_sounds_enabled" value="0" package="android" defaultValue="0" defaultSysSet="true" />
  <setting id="44" name="wifi_scan_always_enabled" value="0" package="android" defaultValue="0" defaultSysSet="true" />
  <setting id="339" name="bluetooth_a2dp_src_priority_54:3A:D6:28:63:9C" value="100" package="com.android.bluetooth" defaultValue="100" defaultSysSet="true" />
  <setting id="260" name="bluetooth_headset_priority_CC:D2:81:78:AB:5F" value="0" package="com.android.bluetooth" defaultValue="0" defaultSysSet="true" />
  <setting id="63" name="external_surround_sound_enabled" value="0" package="android" defaultValue="0" defaultSysSet="true" />
  <setting id="91" name="network_recommendations_enabled" value="0" package="android" defaultValue="0" defaultSysSet="true" />
  <setting id="256" name="bluetooth_a2dp_sink_priority_98:06:3C:25:FF:CF" value="-1" package="com.android.bluetooth" defaultValue="-1" defaultSysSet="true" />
  <setting id="51" name="captive_portal_fallback_url" value="http://fireoscaptiveportal.com/generate_204" package="android" defaultValue="http://fireoscaptiveportal.com/generate_204" defaultSysSet="true" />
  <setting id="95" name="bluetooth_headset_priority_F4:4E:FD:C6:29:FC" value="100" package="com.android.bluetooth" defaultValue="100" defaultSysSet="true" />
  <setting id="57" name="perfboost_appstart_duration" value="200" package="android" defaultValue="200" defaultSysSet="true" />
  <setting id="50" name="captive_portal_http_url" value="http://mmechocaptiveportal.com/generate_204" package="android" defaultValue="http://mmechocaptiveportal.com/generate_204" defaultSysSet="true" />
  <setting id="199" name="persist.sys.ota.isScreenOffBeforeOTA" value="false" package="android" defaultValue="false" defaultSysSet="true" />
  <setting id="33" name="car_dock_sound" value="/system/media/audio/ui/Dock.ogg" package="android" defaultValue="/system/media/audio/ui/Dock.ogg" defaultSysSet="true" />
  <setting id="251" name="bluetooth_headset_priority_54:3A:D6:28:63:9C" value="0" package="com.android.bluetooth" defaultValue="0" defaultSysSet="true" />
  <setting id="52" name="captive_portal_use_https" value="0" package="android" defaultValue="0" defaultSysSet="true" />
  <setting id="75" name="sound_trigger_detection_service_op_timeout" value="15000" package="android" defaultValue="15000" defaultSysSet="true" />
  <setting id="27" name="power_sounds_enabled" value="1" package="android" defaultValue="1" defaultSysSet="true" />
  <setting id="7" name="stay_on_while_plugged_in" value="0" package="android" defaultValue="0" defaultSysSet="true" />
  <setting id="246" name="zen_mode_config_etag" value="201852538" package="android" defaultValue="201852538" defaultSysSet="true" />
  <setting id="37" name="set_install_location" value="0" package="android" defaultValue="0" defaultSysSet="true" />
  <setting id="110" name="com.amazon.oobe.registration.eulaFlag" value="1" package="com.amazon.kindle.otter.oobe" />
  <setting id="82" name="zen_mode" value="0" package="android" defaultValue="0" defaultSysSet="true" />
  <setting id="11" name="transition_animation_scale" value="1.0" package="android" defaultValue="1.0" defaultSysSet="true" />
  <setting id="105" name="device_has_screen_reader_user" value="1" package="com.amazon.logan" defaultValue="0" defaultSysSet="true" />
  <setting id="49" name="captive_portal_https_url" value="http://mmechocaptiveportal.com/generate_204" package="android" defaultValue="http://mmechocaptiveportal.com/generate_204" defaultSysSet="true" />
  <setting id="17" name="data_roaming" value="0" package="android" defaultValue="0" defaultSysSet="true" />
  <setting id="66" name="surround_sound_supported" value="1" package="android" defaultValue="1" defaultSysSet="true" />
  <setting id="103" name="security_sync_client_app_version" value="1.0.200717.0_13001110" package="com.amazon.securitysyncclient" />
  <setting id="12" name="package_verifier_enable" value="1" package="android" defaultValue="1" defaultSysSet="true" />
  <setting id="83" name="audio_platform_capabilities" value='{"audiocaps":{"continuousAudio":true,"pcm":{"mixing":true,"transition":"ease"},"ddplus":{"mixing":true,"transition":"ease"},"atmos":{"enabled":false,"mixing":true,"transition":"ease"}}}' package="android" defaultValue='{"audiocaps":{"continuousAudio":true,"pcm":{"mixing":true,"transition":"ease"},"ddplus":{"mixing":true,"transition":"ease"},"atmos":{"enabled":false,"mixing":true,"transition":"ease"}}}' defaultSysSet="true" />
  <setting id="1" name="theater_mode_on" value="0" package="android" defaultValue="0" defaultSysSet="true" />
  <setting id="336" name="bluetooth_a2dp_sink_priority_F4:4E:FD:C6:29:FC" value="100" package="com.android.bluetooth" defaultValue="100" defaultSysSet="true" />
  <setting id="16" name="cdma_cell_broadcast_sms" value="1" package="android" defaultValue="1" defaultSysSet="true" />
  <setting id="0" name="airplane_mode_on" value="0" package="android" defaultValue="0" defaultSysSet="true" />
  <setting id="62" name="nrdp_external_surround_sound_enabled" value="0" package="android" defaultValue="0" defaultSysSet="true" />
  <setting id="78" name="zen_settings_suggestion_viewed" value="0" package="android" defaultValue="0" defaultSysSet="true" />
  <setting id="70" name="default_restrict_background_data" value="0" package="android" defaultValue="0" defaultSysSet="true" />
  <setting id="28" name="low_battery_sound" value="/system/media/audio/ui/LowBattery.ogg" package="android" defaultValue="/system/media/audio/ui/LowBattery.ogg" defaultSysSet="true" />
  <setting id="337" name="bluetooth_a2dp_sink_priority_54:3A:D6:28:63:9C" value="100" package="com.android.bluetooth" defaultValue="100" defaultSysSet="true" />
  <setting id="191" name="privacy_status" value="0" package="android" defaultValue="0" defaultSysSet="true" />
  <setting id="20" name="netstats_enabled" value="1" package="android" defaultValue="1" defaultSysSet="true" />
  <setting id="69" name="wifi_wakeup_enabled" value="1" package="android" defaultValue="1" defaultSysSet="true" />
  <setting id="104" name="wifi_verbose_logging_enabled" value="0" package="android" defaultValue="0" defaultSysSet="true" />
  <setting id="55" name="dropbox_reserve_percent" value="1" package="android" defaultValue="1" defaultSysSet="true" />
  <setting id="124" name="home_auto_cycle" value="1" package="com.android.settings" defaultValue="1" defaultSysSet="true" />
  <setting id="249" name="bluetooth_headset_priority_08:66:98:BA:55:F4" value="0" package="com.android.bluetooth" defaultValue="0" defaultSysSet="true" />
  <setting id="60" name="com.amazon.tv.settings.VIDEO_QUALITY" value="2" package="android" defaultValue="2" defaultSysSet="true" />
  <setting id="42" name="subscription_mode" value="0" package="android" defaultValue="0" defaultSysSet="true" />
  <setting id="4" name="assisted_gps_enabled" value="1" package="android" defaultValue="1" defaultSysSet="true" />
  <setting id="24" name="lock_sound" value="/system/media/audio/ui/Lock.ogg" package="android" defaultValue="/system/media/audio/ui/Lock.ogg" defaultSysSet="true" />
  <setting id="125" name="auto_time_zone" value="0" package="com.android.settings" defaultValue="0" defaultSysSet="true" />
  <setting id="185" name="wifi_on" value="1" package="android" defaultValue="1" defaultSysSet="true" />
  <setting id="72" name="wireless_charging_started_sound" value="/system/media/audio/ui/ChargingStarted.ogg" package="android" defaultValue="/system/media/audio/ui/ChargingStarted.ogg" defaultSysSet="true" />
  <setting id="113" name="device_provisioned" value="1" package="com.amazon.kindle.otter.oobe" defaultValue="0" defaultSysSet="true" />
  <setting id="89" name="emergency_affordance_needed" value="0" package="android" defaultValue="0" defaultSysSet="true" />
  <setting id="123" name="current_weather" value="1" package="com.android.settings" defaultValue="1" defaultSysSet="true" />
  <setting id="58" name="perfboost_dumptraces_duration" value="500" package="android" defaultValue="500" defaultSysSet="true" />
  <setting id="53" name="captive_portal_mode" value="1" package="android" defaultValue="1" defaultSysSet="true" />
  <setting id="5" name="auto_time" value="1" package="android" defaultValue="1" defaultSysSet="true" />
  <setting id="21" name="usb_mass_storage_enabled" value="1" package="android" defaultValue="1" defaultSysSet="true" />
  <setting id="112" name="wifi_p2p_device_name" value="Amazing Assistant" package="android" defaultValue="Amazing Assistant" defaultSysSet="true" />
  <setting id="119" name="show_home_sharedwithyou" value="1" package="com.android.settings" defaultValue="1" defaultSysSet="true" />
  <setting id="40" name="call_auto_retry" value="0" package="android" defaultValue="0" defaultSysSet="true" />
  <setting id="118" name="show_home_photomemories" value="0" package="com.android.settings" defaultValue="0" defaultSysSet="true" />
  <setting id="121" name="show_home_trending_stories" value="1" package="com.android.settings" defaultValue="1" defaultSysSet="true" />
  <setting id="106" name="broadcast_sync_enabled" value="0" package="android" defaultValue="0" defaultSysSet="true" />
  <setting id="102" name="audio_safe_volume_state" value="3" package="android" defaultValue="3" defaultSysSet="true" />
  <setting id="198" name="boot_count" value="13" package="android" defaultValue="13" defaultSysSet="true" />
  <setting id="31" name="desk_dock_sound" value="/system/media/audio/ui/Dock.ogg" package="android" defaultValue="/system/media/audio/ui/Dock.ogg" defaultSysSet="true" />
  <setting id="255" name="bluetooth_input_device_priority_98:06:3C:25:FF:CF" value="-1" package="com.android.bluetooth" defaultValue="-1" defaultSysSet="true" />
  <setting id="54" name="dropbox_quota_percent" value="80" package="android" defaultValue="80" defaultSysSet="true" />
</settings>                                                                                                                                                                                                                                                                                                                                                                                                                                                                                                                                                                                                                                                                                                                                                                                                                                                                                                                                                                                                                                                                                                                                                                                                                                                                                                                                                                                                                                                                                                                                                                                                                                                                                                      