<?xml version='1.0' encoding='utf-8' standalone='yes' ?>
<map>
    <int name="230" value="53" />
    <int name="110" value="99" />
    <int name="231" value="130" />
    <int name="111" value="16" />
    <int name="232" value="223" />
    <int name="112" value="192" />
    <int name="233" value="131" />
    <int name="113" value="267" />
    <int name="234" value="80" />
    <int name="114" value="180" />
    <int name="115" value="186" />
    <int name="116" value="137" />
    <int name="117" value="156" />
    <int name="118" value="76" />
    <int name="119" value="307" />
    <int name="10" value="10" />
    <int name="11" value="38" />
    <int name="12" value="75" />
    <int name="13" value="7" />
    <int name="14" value="429" />
    <int name="15" value="242" />
    <int name="16" value="386" />
    <int name="17" value="313" />
    <int name="18" value="104" />
    <int name="19" value="160" />
    <int name="120" value="265" />
    <int name="121" value="399" />
    <int name="1" value="2" />
    <int name="122" value="280" />
    <int name="2" value="171" />
    <int name="123" value="324" />
    <int name="3" value="226" />
    <int name="124" value="217" />
    <int name="4" value="114" />
    <int name="125" value="10" />
    <int name="5" value="262" />
    <int name="126" value="195" />
    <int name="6" value="45" />
    <int name="127" value="180" />
    <int name="7" value="149" />
    <int name="128" value="63" />
    <int name="8" value="100" />
    <int name="129" value="13" />
    <int name="9" value="8" />
    <int name="20" value="315" />
    <int name="21" value="217" />
    <int name="22" value="188" />
    <int name="23" value="152" />
    <int name="24" value="260" />
    <int name="25" value="186" />
    <int name="26" value="137" />
    <int name="27" value="247" />
    <int name="28" value="143" />
    <int name="29" value="330" />
    <int name="130" value="7" />
    <int name="131" value="32" />
    <int name="132" value="223" />
    <int name="133" value="41" />
    <int name="134" value="5" />
    <int name="135" value="48" />
    <int name="136" value="188" />
    <int name="137" value="45" />
    <int name="138" value="148" />
    <int name="139" value="150" />
    <int name="30" value="104" />
    <int name="31" value="20" />
    <int name="32" value="295" />
    <int name="33" value="321" />
    <int name="34" value="282" />
    <int name="35" value="216" />
    <int name="36" value="155" />
    <int name="37" value="312" />
    <int name="38" value="153" />
    <int name="39" value="327" />
    <long name="RecordedEventsPrefsKey" value="2" />
    <int name="140" value="209" />
    <int name="141" value="102" />
    <int name="142" value="281" />
    <int name="143" value="218" />
    <int name="144" value="4" />
    <int name="145" value="5" />
    <int name="146" value="8" />
    <int name="147" value="225" />
    <int name="148" value="247" />
    <int name="149" value="100" />
    <int name="40" value="245" />
    <int name="41" value="271" />
    <int name="42" value="322" />
    <int name="43" value="390" />
    <int name="44" value="256" />
    <int name="45" value="137" />
    <int name="46" value="90" />
    <int name="47" value="166" />
    <int name="48" value="205" />
    <int name="49" value="296" />
    <int name="150" value="238" />
    <int name="151" value="176" />
    <int name="152" value="360" />
    <int name="153" value="74" />
    <int name="154" value="308" />
    <int name="155" value="380" />
    <int name="156" value="95" />
    <int name="157" value="14" />
    <int name="158" value="220" />
    <int name="159" value="147" />
    <int name="50" value="259" />
    <int name="51" value="158" />
    <int name="52" value="82" />
    <int name="53" value="95" />
    <int name="54" value="110" />
    <int name="55" value="368" />
    <int name="56" value="278" />
    <int name="57" value="242" />
    <int name="58" value="328" />
    <int name="59" value="96" />
    <int name="160" value="55" />
    <int name="161" value="63" />
    <int name="162" value="157" />
    <int name="163" value="144" />
    <int name="164" value="200" />
    <int name="165" value="202" />
    <int name="166" value="373" />
    <int name="167" value="116" />
    <int name="168" value="116" />
    <int name="169" value="174" />
    <int name="60" value="420" />
    <int name="61" value="308" />
    <int name="62" value="236" />
    <int name="63" value="383" />
    <int name="64" value="346" />
    <int name="65" value="182" />
    <int name="66" value="338" />
    <int name="67" value="26" />
    <int name="68" value="215" />
    <int name="69" value="162" />
    <int name="170" value="36" />
    <int name="171" value="253" />
    <int name="172" value="12" />
    <int name="173" value="239" />
    <int name="174" value="116" />
    <int name="175" value="198" />
    <int name="176" value="162" />
    <boolean name="IS_UPGRADED" value="true" />
    <int name="177" value="89" />
    <int name="178" value="161" />
    <int name="179" value="139" />
    <int name="70" value="235" />
    <int name="71" value="146" />
    <int name="72" value="135" />
    <int name="73" value="142" />
    <int name="74" value="197" />
    <int name="75" value="187" />
    <int name="76" value="283" />
    <int name="77" value="377" />
    <int name="78" value="21" />
    <int name="79" value="7" />
    <int name="180" value="347" />
    <int name="181" value="187" />
    <int name="182" value="133" />
    <int name="183" value="55" />
    <int name="184" value="46" />
    <int name="185" value="132" />
    <int name="186" value="144" />
    <int name="187" value="49" />
    <int name="188" value="182" />
    <int name="189" value="49" />
    <int name="80" value="171" />
    <int name="81" value="196" />
    <int name="82" value="61" />
    <int name="83" value="77" />
    <int name="84" value="56" />
    <int name="85" value="10" />
    <int name="86" value="57" />
    <int name="87" value="159" />
    <int name="88" value="7" />
    <int name="89" value="33" />
    <int name="190" value="159" />
    <int name="191" value="304" />
    <int name="192" value="186" />
    <int name="193" value="272" />
    <int name="194" value="51" />
    <int name="195" value="192" />
    <int name="196" value="5" />
    <int name="197" value="48" />
    <int name="198" value="48" />
    <int name="199" value="293" />
    <int name="90" value="190" />
    <int name="91" value="72" />
    <int name="92" value="129" />
    <int name="93" value="323" />
    <int name="94" value="16" />
    <int name="95" value="118" />
    <int name="96" value="92" />
    <int name="97" value="89" />
    <int name="98" value="68" />
    <int name="99" value="98" />
    <int name="200" value="120" />
    <int name="201" value="2" />
    <int name="202" value="3" />
    <int name="203" value="118" />
    <int name="204" value="13" />
    <int name="205" value="48" />
    <int name="206" value="241" />
    <int name="207" value="221" />
    <int name="208" value="199" />
    <int name="209" value="198" />
    <int name="210" value="2" />
    <int name="211" value="294" />
    <int name="212" value="125" />
    <int name="213" value="260" />
    <int name="214" value="132" />
    <int name="215" value="108" />
    <int name="216" value="7" />
    <int name="217" value="279" />
    <int name="218" value="126" />
    <int name="219" value="103" />
    <int name="220" value="113" />
    <int name="100" value="163" />
    <int name="221" value="246" />
    <int name="101" value="100" />
    <int name="222" value="136" />
    <int name="102" value="138" />
    <int name="223" value="33" />
    <int name="103" value="172" />
    <int name="224" value="87" />
    <int name="104" value="18" />
    <int name="225" value="85" />
    <int name="105" value="147" />
    <int name="226" value="201" />
    <int name="106" value="7" />
    <int name="227" value="318" />
    <int name="107" value="2" />
    <int name="228" value="125" />
    <int name="108" value="21" />
    <int name="229" value="37" />
    <int name="109" value="113" />
</map>
                               [n*H
r_jfi?EiQ@Uk"ǽȗ'&+>)d Yh!0Kq<Y˪i7ӻ-xut9ǩ3?z%V?lU>?ٚIBsw5c{( #1ɥꮫ+
7-ӳCI1u{9[! L0ܖhܢ ,UsYk'-ٖ
 ؖoy iͰ:hGeKkӬB׫U=Rmd-mrB WW/? > 9&}9!_}wEj|EtgG-<ȑ?d-My^5*3wNc!lRw3Ձw>Kۉ666V9iF햋 e}:KVQCݒ7<hȮ'AdD	7y))ܨ8Hu^-NO<ufYیͫ G8UâKG-״aۖg}E1+6e3\Uz3 [6wi<'Agi4..w\#4vTbo+~WaFV47 Fo&Ƈۅ<B6GIx8j|;vUJf3m&124׏Eѻ΅L
,^zEIHSNW%`, CZSŽ6 rW[T$LcKA
A~FV%v;ex^nK93vдXPD!@X^u9AD~fm/zgX18'Dʵ DiƱsV_w-ך: oh,C$op (9u?Ug7v|_X۝fَW}ÌyNEsPYbD<=q߀73(j~Fr,I*Yq+V5%`eCgPnCxv,qfI.j9 8aSE*;ܻtltOiR'z3ׄ?
(ckǌ1LPL[TgͶZDf)	`!g"m+ A M=(F"瀥2KktX#̑d
,HSp&:cpFd`Vܦ}jH(5w%rB*F-joQ n8YH㾿2䫆B I =Z^YDg5
+j'UZr
HA"	dYzEqZlU/Y қ`xW|^(fR=-q@Lf>Wyu#>GȢd
?r|`i[<;]E頺~bŲ(BdKyBss5X:1ÅLtyp"p!cjxfb6/<9[	o2.o=Go{e'ql_2c^ IZ<5_RE-lwf	x"GEHwivJj<kYF^R/˃҃ :>-}诀Ju(hr7TЬUVp}H($ &0R%߫` '.<Z:u{TJpg>o-4@%VJessuq_^u_7GU~4,}:-"p閝cKE$ Tv|&*U«5)ʋ2]xJmˎQfxX2j8+^|/iU:)v)f51>w4m3K°lK-
!;oRۚi^iu{ԋ7ns644Ͷ	̷o	)otA)uf؉ʠQti=$ !` =QVyz]\5ƫemx/+"Pװ]REf㽠Usv"+4TDjE,k˫Jձ<`r6@cڤ]z$ɚ-`KXo
a[ ?.ϙd9ێmr.;R 6qsrB%\q&˓o'dN1ě'mSp^f!{;<d#ۮkԠnSB_E\n8 q>1LY)C,yЗ	RII!qlǦ+-^u.L^-_{$'2j}z{+}LgN?GNGGfY6TH](k/]AU3꘯o_fr>ќP x	 ־
j^ب/~	 tjoMzI>7Glקbjzvejn}QTqeZe[6%Kj+[h5>z^`_cf Yv9nI2Mف|8^v&oVrlH=<e{Y <|56N A)i;az8Nv!b<NLN`2-/+Jàfޯ^^:$w._;u,q8~9y-:cˣDf˗_St[+Q2}TæxBZ1.r|fhAUnb^Mz}x/4=Q7jDqjHlc?PKX  _P  PK   n~WW            
   Log.main_8\kSJbl,en\z$KF+Ȓ$s`,ƐzIŶtOwO=#PHrzMH䳏T4w7vԩ)Pu7e"袣Aq\JQXg"1}SO-ǴAUCݑ嫋6UtvZ<FQG0R}F6FHEwUQknNdo54R
+Tҕ1pNnRLgdIeijyVX])MXE;͸T4 iBIQ%yGUuЗ~X!4*HW_E=tjU֦+>2d	tѡJ#6"G$h%i%a0~3?@xF5S9ZnJwQGEYoi.~C:H'~C|ߞ<i׈wXFXۺԺ7֍gxrƺ=m>Kc_鹶|=0	y &1L9kAR:JU3(zzSU	]g*,XvҬ먟u
söA['NӗCJ#hOhRGZ]1/JbyC8<L<G1AOd}v")+	
D0\{-ō㑂1Ch^\Nơ43](AYucwr-LQ?ᬌ;g;T\1̋5fa>"'ޯ/dNjpFy:ҠZOS*{ɘhUKҪۘC	>8Ǐ\/jzLgF8",ʅ,F.+ho[ԇTG:Lsͽ'10Fff,$,28guZCtc]+8hb#P4ôw~(8 *j¢?C]j8z>/SxN
,x)\zC3m٫i7sH&MGqyבHCjst3ou u`x(l`yb\u@:9ŰwnZ]VEn~1z</^mciYE2La0HF@+ڜy1$ejلc8XY3aφPMضymKO$mdpl?}見 hw۱*Ex Ue3fS#:vmgt>ޡjVQls77a ܇iՌ[٭:W00f\;K'tKJ,C@eRn4d  pxĎdw'HPI,5MȮu]cc0-cy[ 8l2Qa,?4sֱS; #Icq
H퉥mno˙4>u| S({H/}G	&/eE?h VGήvEz=?,%L8]JMC Y!0n\;v	!V1#mOj9:~\C-/oEKpSeLwprH::;4:}&|<Xrh:(!sU
##Рpf	i^edUۄ!kS5׵dI&}EA<p	&yf(,F !uc?d..ts)im=GNd=FM;&S
zjkQnQo.a<*^2  Aᡥ
Ȃ>=tYbQZrAO}z
iA
B ,+0I
[7!Y@T0xEGRݔy.% kf-rg@e̮4#DRm*LV>pJ		b.jڈ]A@1!%8.8pp4Z>pOnMC@<m	sҙw{uN4dR%<' iS<.I97Z]-mCѸ5eWUzz'\Kd0n!>$|2\;abgxR3HO&:N[KwF|4b6<Ck&qq[yqݣbr5)xkaW*f;qn SYaOqA.ּQZg#8\aUX#utD T@MFCcǵqEΊHp[ 7ɞH閼@&hN(qrjFյ ô2g׵vtf՝Anæ[5>HKXd=DԬx."ڄ=L̆\X`7]{m:Jmkj*g|RW% .b`HٶLE$%`џV5"k#E.Ǎ3Oq6bbr̨jG,6B ˷j#@o
ؿ6<6Uj#v&]k#>:Rz8¤뜺һ>y0k/c60ѱiG(ZOJ\/EGLRs(<ZzF>UG|Ho~{B{w~&_ɽɸcoўVE.n2^fceCwPAZk_bNU|_-)ux?&Oeꆟif~O_il)n8YMt 0mnάlw\FE\<8:2#:73qZ{h%vy_d	,Zhmfvړ {{[_MN0~]hM$3SbEMڢWr#>kܾyQjS%>"p֐ J(ţ(rfz*5[g$\qY>=ٌIٚKP5j-WF	1Yǻ	G B=ulGȀdeWR2khpkmz}CLQٲ^WDs* i	fu=> TKpD/Gj#?Tv!峩1p4rS={Xyj:FȜ8ð@I"	JSn6M&u=W,I5mCf8k{t#3@@oW|b2 !`&̝].M㋫Z\i8lFLKD0}g2deЖ[J˖o0}h>b\+Tb
|hL.6I	OzpTBZ58q~,$&1#۽h-E[eT7ԵKLALxvKtU!%.6&L
|rVCX縈Fs_g?D~x+6kϿ/'Ocm'bv(	|/Xk{>V.0G2Fpaie[şeju1-:&"{"c:@xCIB|c^Ldܪ۔pݞʲPEg]R"((\nK)`0dSrU\Di*=NB ($~0ixp/Ǌ3""ءb7dx>g-,1̽5!`RBy6TlAӺCzsTY~H>ӂ	~?|q^J\}LWK9[W[J"I)v͟OujխBյku;@lќ`oj"RCCS[65&&4kiF:c[}Pg
OVR"$$LC^/&wn"jX}%!JE0#l6E.21o6{
*B7U:KYּIefڍØ_c/4Ȉ`2CO`"=O$O` hiiОPϮ=ٲ^o,[41J}b^戭ßZ2*kքckh`^)cc=uߋ4W_>gLEd_fOo$<~?rU&;E|^fG^OG6 ~i_ޓG7m<><D/Ǘ?~&q7s@ϽE
/.M9dk7fgwc6LѨ(28tz	Л!>W~2|.l"2Zÿo[>vJvJoG.zŷOh!a6t'PK?b  9P  PK   p~WW            
   Log.main_9\n۸ߧ 큥H6mwӦAm/"D*F\Iv]컟䤶e;8H,[~CLQDXK4}>Qe25N"345EU}'#
gs2F*)(TQf?P"/dIѐJ'5wIQVtP2Br]>"=t"G~\ë:34FcG&Uajа@e41A3Zӌ(I9O($4IG_1.̉gQ6tPr`gecC8Ɓ
FD(׆J&I6@ؑTJǗR;|G1"7QŦi/^n<)lG5ҩ}2TgвZ:iR~mJFׁPٺp<?xml version='1.0' encoding='utf-8' standalone='yes' ?>
<map>
    <int name="230" value="53" />
    <int name="110" value="99" />
    <int name="231" value="130" />
    <int name="111" value="16" />
    <int name="232" value="223" />
    <int name="112" value="192" />
    <int name="233" value="131" />
    <int name="113" value="267" />
    <int name="234" value="88" />
    <int name="114" value="180" />
    <int name="115" value="186" />
    <int name="116" value="137" />
    <int name="117" value="156" />
    <int name="118" value="76" />
    <int name="119" value="307" />
    <int name="10" value="10" />
    <int name="11" value="38" />
    <int name="12" value="75" />
    <int name="13" value="7" />
    <int name="14" value="429" />
    <int name="15" value="242" />
    <int name="16" value="386" />
    <int name="17" value="313" />
    <int name="18" value="104" />
    <int name="19" value="160" />
    <int name="120" value="265" />
    <int name="121" value="399" />
    <int name="1" value="2" />
    <int name="122" value="280" />
    <int name="2" value="171" />
    <int name="123" value="324" />
    <int name="3" value="226" />
    <int name="124" value="217" />
    <int name="4" value="114" />
    <int name="125" value="10" />
    <int name="5" value="262" />
    <int name="126" value="195" />
    <int name="6" value="45" />
    <int name="127" value="180" />
    <int name="7" value="149" />
    <int name="128" value="63" />
    <int name="8" value="100" />
    <int name="129" value="13" />
    <int name="9" value="8" />
    <int name="20" value="315" />
    <int name="21" value="217" />
    <int name="22" value="188" />
    <int name="23" value="152" />
    <int name="24" value="260" />
    <int name="25" value="186" />
    <int name="26" value="137" />
    <int name="27" value="247" />
    <int name="28" value="143" />
    <int name="29" value="330" />
    <int name="130" value="7" />
    <int name="131" value="32" />
    <int name="132" value="223" />
    <int name="133" value="41" />
    <int name="134" value="5" />
    <int name="135" value="48" />
    <int name="136" value="188" />
    <int name="137" value="45" />
    <int name="138" value="148" />
    <int name="139" value="150" />
    <int name="30" value="104" />
    <int name="31" value="20" />
    <int name="32" value="295" />
    <int name="33" value="321" />
    <int name="34" value="282" />
    <int name="35" value="216" />
    <int name="36" value="155" />
    <int name="37" value="312" />
    <int name="38" value="153" />
    <int name="39" value="327" />
    <long name="RecordedEventsPrefsKey" value="2" />
    <int name="140" value="209" />
    <int name="141" value="102" />
    <int name="142" value="281" />
    <int name="143" value="218" />
    <int name="144" value="4" />
    <int name="145" value="5" />
    <int name="146" value="8" />
    <int name="147" value="225" />
    <int name="148" value="247" />
    <int name="149" value="100" />
    <int name="40" value="245" />
    <int name="41" value="271" />
    <int name="42" value="322" />
    <int name="43" value="390" />
    <int name="44" value="256" />
    <int name="45" value="137" />
    <int name="46" value="90" />
    <int name="47" value="166" />
    <int name="48" value="205" />
    <int name="49" value="296" />
    <int name="150" value="238" />
    <int name="151" value="176" />
    <int name="152" value="360" />
    <int name="153" value="74" />
    <int name="154" value="308" />
    <int name="155" value="380" />
    <int name="156" value="95" />
    <int name="157" value="14" />
    <int name="158" value